Cselenium/CSelenium.py
Cselenium/Personification.py
Cselenium/RandomData.py
Cselenium/__init__.py
Cselenium/CSAbstract/CSeleniumABS.py
Cselenium/CSAbstract/__init__.py
Cselenium/CSError/Error.py
Cselenium/CSError/__init__.py
Cselenium/CSLanguage/Language.py
Cselenium/CSLanguage/__init__.py
Cselenium/TestHttp/TestHTTP.py
Cselenium/TestHttp/__init__.py
Cselenium/TestHttp/lx_test.py
Cselenium/TestReport/HtmlTestReport.py
Cselenium/TestReport/__init__.py
CSelenium-0.0.7.dist-info/LICENSE
CSelenium-0.0.7.dist-info/METADATA
CSelenium-0.0.7.dist-info/WHEEL
CSelenium-0.0.7.dist-info/top_level.txt
CSelenium-0.0.7.dist-info/RECORD
