Metadata-Version: 2.1
Name: CSelenium
Version: 0.0.7
Summary: Simplify native Selenium operations to locate elements in a shorter manner
Home-page: https://github.com/LX-sys/CSelenium
Author: LX
Author-email: lx984608061@163.com
Maintainer: LX
Maintainer-email: lx984608061@163.com
License: BSD License
Platform: all
Classifier: Development Status :: 4 - Beta
Classifier: Operating System :: OS Independent
Classifier: Intended Audience :: Developers
Classifier: License :: OSI Approved :: BSD License
Classifier: Programming Language :: Python
Classifier: Programming Language :: Python :: Implementation
Classifier: Programming Language :: Python :: 3.6
Classifier: Programming Language :: Python :: 3.8
Classifier: Topic :: Software Development :: Libraries
Requires-Python: >=3.6
License-File: LICENSE
Requires-Dist: bs4
Requires-Dist: selenium
